[
  {
    "technicianCount": 20,
    "cmsNeeded": 2
  },
  {
    "technicianCount": 19,
    "cmsNeeded": 2
  },
  {
    "technicianCount": 18,
    "cmsNeeded": 2
  },
  {
    "technicianCount": 17,
    "cmsNeeded": 2
  },
  {
    "technicianCount": 16,
    "cmsNeeded": 2
  },
  {
    "technicianCount": 15,
    "cmsNeeded": 2
  },
  {
    "technicianCount": 14,
    "cmsNeeded": 2
  },
  {
    "technicianCount": 13,
    "cmsNeeded": 2
  },
  {
    "technicianCount": 12,
    "cmsNeeded": 2
  },
  {
    "technicianCount": 11,
    "cmsNeeded": 2
  },
  {
    "technicianCount": 10,
    "cmsNeeded": 1
  },
  {
    "technicianCount": 9,
    "cmsNeeded": 1
  },
  {
    "technicianCount": 8,
    "cmsNeeded": 1
  },
  {
    "technicianCount": 7,
    "cmsNeeded": 1
  },
  {
    "technicianCount": 6,
    "cmsNeeded": 1
  },
  {
    "technicianCount": 5,
    "cmsNeeded": 1
  },
  {
    "technicianCount": 4,
    "cmsNeeded": 1
  },
  {
    "technicianCount": 3,
    "cmsNeeded": 1
  },
  {
    "technicianCount": 2,
    "cmsNeeded": 1
  },
  {
    "technicianCount": 1,
    "cmsNeeded": 1
  }
]